pyready/__init__.py
pyready/base.py
pyready/postgres.py
pyready/telnet.py
pyready-0.0.7.dist-info/DESCRIPTION.rst
pyready-0.0.7.dist-info/METADATA
pyready-0.0.7.dist-info/RECORD
pyready-0.0.7.dist-info/WHEEL
pyready-0.0.7.dist-info/metadata.json
pyready-0.0.7.dist-info/top_level.txt
